slicetune/__init__.py
slicetune/model.py
slicetune/nn.py
slicetune/utils.py
slicetune-0.0.1.dist-info/METADATA
slicetune-0.0.1.dist-info/WHEEL
slicetune-0.0.1.dist-info/RECORD
