Metadata-Version: 2.1
Name: slicetune
Version: 0.0.1
Summary: A non-invasive parameter-efficient method for finetuning large neural models.
License: MIT
Author: Marek Kadlcik
Author-email: 10684818+markcheeky@users.noreply.github.com
Requires-Python: >=3.8.1,<4.0.0
Classifier: License :: OSI Approved :: MIT License
Classifier: Programming Language :: Python :: 3
Classifier: Programming Language :: Python :: 3.9
Classifier: Programming Language :: Python :: 3.10
Classifier: Programming Language :: Python :: 3.11
Provides-Extra: pretty
Requires-Dist: prettytable (>=3.0.0) ; extra == "pretty"
Requires-Dist: torch (>=1.8)
Requires-Dist: typing-extensions (>=4.4.0,<5.0.0)
